README.md
setup.py
JCoder_redis/JCoder_redis.py
JCoder_redis/__init__.py
JCoder_redis/ordered_set.py
JCoder_redis/redis_dict.py
JCoder_redis/redis_float.py
JCoder_redis/redis_int.py
JCoder_redis/redis_list.py
JCoder_redis/redis_set.py
JCoder_redis/redis_string.py
JCoder_redis.egg-info/PKG-INFO
JCoder_redis.egg-info/SOURCES.txt
JCoder_redis.egg-info/dependency_links.txt
JCoder_redis.egg-info/requires.txt
JCoder_redis.egg-info/top_level.txt
jcoder_redis/__init__.py
jcoder_redis/jcoder_redis.py
jcoder_redis/ordered_set.py
jcoder_redis.egg-info/PKG-INFO
jcoder_redis.egg-info/SOURCES.txt
jcoder_redis.egg-info/dependency_links.txt
jcoder_redis.egg-info/requires.txt
jcoder_redis.egg-info/top_level.txt