Metadata-Version: 2.1
Name: JCoder-redis
Version: 0.0.5
Summary: This Redis is a Python library based on redis.
Home-page: https://github.com/satans404/repackaged_redis_for_JCoder
Author: satan404
Author-email: 11912823@mail.sustech.edu.cn
License: UNKNOWN
Platform: UNKNOWN
Classifier: Programming Language :: Python :: 3
Classifier: License :: OSI Approved :: MIT License
Classifier: Operating System :: OS Independent
